{
	"sdkSettings" : {
		"version" : "2.0",
		"host" : "https://onedemo.thunderhead.com",
		"touchpoint" : "oeh://assisted",
		"sk" : "ONE-BIVBFTID4P-1647",
		"oauth1" : {
			"apiKey" : "eff883bb-d4e5-4d0e-bba0-7c7094c3c112",
			"sharedSecret" : "f22413d6-1667-46e5-bfcb-e0f9c61cb445",
			"loginId" : "alee@onedemo-presales"
		}
	},
	"aepPanelDef" : {
		"structure" : "history",
		"format" : "json"
	},
	"devicePanelDef" : {
		"structure" : "devices",
		"format" : "json"
	},
	"historyPanelDef" : {
		"structure" : "history",
		"format" : "json"
	},
    "customerPanelDef" : {
		"structure" : "aep",
		"format" : "json"
	},
	"nbcPanelDef" : {
		"interaction" : "/nbc"
	},
	"scjPanelDef" : {
		"dataStructure": "SingleCustomerJourney",
		"configStructure": "Configuration"
	}
    
    
}
